{
  "captured_at_ts": 10405.0,
  "height": 0,
  "metadata": {
    "condition_ratio": 1.0,
    "cycle_id": 229,
    "hp_ratio": 1.0,
    "in_combat": false,
    "perception_profile": {
      "action_ready_duration_s": 0.002,
      "detection_duration_s": 0.011,
      "selection_duration_s": 0.003
    },
    "phase": "observation",
    "rest_available": true,
    "reward_visible": false,
    "targets": [
      {
        "bbox_height": null,
        "bbox_width": null,
        "confidence": 1.0,
        "distance": 4.247377,
        "metadata": {},
        "mob_variant": "mob_a",
        "occupied": false,
        "orientation_deg": 0,
        "reachable": true,
        "screen_x": 700,
        "screen_y": 335,
        "target_id": "live-spawn-229-1"
      },
      {
        "bbox_height": null,
        "bbox_width": null,
        "confidence": 1.0,
        "distance": 4.063578,
        "metadata": {},
        "mob_variant": "mob_b",
        "occupied": false,
        "orientation_deg": 0,
        "reachable": true,
        "screen_x": 728,
        "screen_y": 322,
        "target_id": "live-spawn-229-2"
      },
      {
        "bbox_height": null,
        "bbox_width": null,
        "confidence": 1.0,
        "distance": 4.40246,
        "metadata": {},
        "mob_variant": "mob_a",
        "occupied": false,
        "orientation_deg": 0,
        "reachable": true,
        "screen_x": 644,
        "screen_y": 304,
        "target_id": "live-spawn-229-3"
      }
    ]
  },
  "source": "dry_run:single_spot_mvp",
  "width": 0
}